{"global":0,"info":[{"version":19,"change":[{"flag":"end","value":["/random.js","/easy-Danmaku.js","/echarts.js","/about/","/album/","/bangumis/","/comments/","/copyright/","/dailyPhoto/","/equipment/","/essay/","/blog.cuixinyu.com/","/link/","/privacy/","/statistics/","/update/","/wordScenery/"]},{"flag":"begin","value":["/archives/","/categories/","/tags/"]}]},{"version":18},{"version":17},{"version":16},{"version":15},{"version":14},{"version":13},{"version":12},{"version":11},{"version":10},{"version":9},{"version":8},{"version":7,"change":[{"flag":"end","value":"/owo.json"}]},{"version":6,"change":[{"flag":"end","value":"/cuixinyu.js"}]},{"version":5},{"version":4,"change":[{"flag":"end","value":"/custom.css"}]},{"version":3},{"version":2,"change":[{"flag":"end","value":"/sw-dom.js"}]},{"version":1,"change":[{"flag":"end","value":["off2?t=1690446183540","woff?t=1690446183540",".ttf?t=1690446183540"]}]},{"version":0}]}